paradocs/__init__.py
paradocs-0.0.1.dist-info/METADATA
paradocs-0.0.1.dist-info/WHEEL
paradocs-0.0.1.dist-info/top_level.txt
paradocs-0.0.1.dist-info/RECORD
