Metadata-Version: 2.4
Name: paradocs
Version: 0.0.1
Summary: CLI for generating documents from parameterized Jinja2 templates (in development)
Author: Enrico Kuhn
License: MIT
Project-URL: Homepage, https://github.com/yourusername/paradocs
Classifier: Development Status :: 1 - Planning
Classifier: Intended Audience :: Developers
Classifier: License :: OSI Approved :: MIT License
Classifier: Programming Language :: Python :: 3
Classifier: Programming Language :: Python :: 3.8
Classifier: Programming Language :: Python :: 3.9
Classifier: Programming Language :: Python :: 3.10
Classifier: Programming Language :: Python :: 3.11
Classifier: Programming Language :: Python :: 3.12
Requires-Python: >=3.8
